purolator_lib/__init__.py
purolator_lib/array_ofstring.py
purolator_lib/data_types.py
purolator_lib/estimate_service_2_1_2.py
purolator_lib/freight_data_types.py
purolator_lib/freight_estimate_service_1_1_0.py
purolator_lib/freight_pickup_service_1_1_0.py
purolator_lib/freight_shipment_service_1_1_0.py
purolator_lib/freight_tracking_service_1_1_0.py
purolator_lib/freight_validation_detail.py
purolator_lib/freight_validation_fault.py
purolator_lib/locator_service_1_0_2.py
purolator_lib/pickup_service_1_2_1.py
purolator_lib/returns_management_service_2_0.py
purolator_lib/service_availability_service_2_0_2.py
purolator_lib/shipping_documents_service_1_3_0.py
purolator_lib/shipping_service_2_1_3.py
purolator_lib/tracking_service_1_2_2.py
purolator_lib/validation_detail.py
purolator_lib/validation_fault.py
carrier.purolator-2020.4.1.dist-info/WHEEL
carrier.purolator-2020.4.1.dist-info/METADATA
carrier.purolator-2020.4.1.dist-info/RECORD
